{
  "project_info": {
    "project_number": "947139385047",
    "project_id": "todo-e1bc8",
    "storage_bucket": "todo-e1bc8.appspot.com"
  },
  "client": [
    {
      "client_info": {
        "mobilesdk_app_id": "1:947139385047:android:5e59faee2694699fc80292",
        "android_client_info": {
          "package_name": "com.example.todo"
        }
      },
      "oauth_client": [],
      "api_key": [
        {
          "current_key": "AIzaSyBCVbHBszL_kAkqkqVpqKUi3sJz-ISYrwU"
        }
      ],
      "services": {
        "appinvite_service": {
          "other_platform_oauth_client": []
        }
      }
    }
  ],
  "configuration_version": "1"
}